hwh_backend/__init__.py
hwh_backend/build.py
hwh_backend/hwh_config.py
hwh_backend/logger.py
hwh_backend/parser.py
hwh_backend-0.4.1.dist-info/licenses/LICENSE
hwh_backend-0.4.1.dist-info/METADATA
hwh_backend-0.4.1.dist-info/WHEEL
hwh_backend-0.4.1.dist-info/top_level.txt
hwh_backend-0.4.1.dist-info/RECORD
