Metadata-Version: 2.4
Name: hwh-backend
Version: 0.4.1
Summary: Setuptools based backend supporting Cython extensions
Author-email: Mathias von Essen <3090690+mkgessen@users.noreply.github.com>
License-Expression: MIT
Project-URL: Repository, https://github.com/mkgessen/hwh-backend.git
Keywords: cython,build,backend,pep517
Classifier: Development Status :: 4 - Beta
Classifier: Intended Audience :: Developers
Classifier: Programming Language :: Python :: 3
Classifier: Programming Language :: Python :: 3.11
Classifier: Programming Language :: Cython
Classifier: Topic :: Software Development :: Build Tools
Classifier: Topic :: Software Development :: Libraries :: Python Modules
Classifier: Operating System :: POSIX :: Linux
Requires-Python: >=3.11
License-File: LICENSE
Requires-Dist: setuptools>=68.0
Requires-Dist: wheel>=0.40.0
Requires-Dist: Cython<3.0.0
Requires-Dist: pyproject-metadata>=0.7.0
Provides-Extra: test
Requires-Dist: pytest>=7.0; extra == "test"
Requires-Dist: pytest-cov>=4.0; extra == "test"
Requires-Dist: coverage>=7.0; extra == "test"
Requires-Dist: build>=1.0.0; extra == "test"
Requires-Dist: tomli-w; extra == "test"
Provides-Extra: dev
Requires-Dist: black>=23.0.0; extra == "dev"
Requires-Dist: isort>=5.0.0; extra == "dev"
Requires-Dist: mypy>=1.0.0; extra == "dev"
Requires-Dist: ruff>=0.1.0; extra == "dev"
Requires-Dist: hwh-backend[test]; extra == "dev"
Dynamic: license-file
